{"phrasenums": {"numadjectives": 4, "numstyles": 4, "numquality": 4}, "trueorfalse": {"usepromptmatrix": false, "A1111txt": false, "invokeaitxt": false, "invokehiresfix": false, "invokeaigrid": false}, "A1111txt": {"negativeprompt": "text", "steps": "30", "cfg": "8", "sampler": "DPM++ SDE Karras", "seed": "-1", "width": "512", "height": "512"}, "invokeaitxt": {"negativeprompt": "", "width": "512", "height": "512", "iterations": "1", "steps": "30", "cfg": "8", "seed": "", "sampler": "k_dpmpp_2", "outputdir": "outputs/promptgen"}}